polycon/__init__.py
polycon/lib/.rendered.polycon_bindings_01_FP64.cpp
polycon/lib/.rendered.polycon_bindings_02_FP64.cpp
polycon/lib/.rendered.polycon_bindings_03_FP64.cpp
polycon/lib/.rendered.polycon_bindings_04_FP64.cpp
polycon/lib/.rendered.polycon_bindings_05_FP64.cpp
polycon/lib/.rendered.polycon_bindings_06_FP64.cpp
polycon/lib/.rendered.polycon_bindings_07_FP64.cpp
polycon/lib/.rendered.polycon_bindings_08_FP64.cpp
polycon/lib/.rendered.polycon_bindings_09_FP64.cpp
polycon/lib/.rendered.polycon_bindings_10_FP64.cpp
polycon/lib/PolyCon.py
polycon/lib/__init__.py
polycon/lib/cppimport_cfg.py
polycon/lib/polycon_bindings.h
polycon/lib/polycon_bindings_01_FP64.cpp
polycon/lib/polycon_bindings_01_FP64.cpython-310-darwin.so
polycon/lib/polycon_bindings_02_FP64.cpp
polycon/lib/polycon_bindings_02_FP64.cpython-310-darwin.so
polycon/lib/polycon_bindings_03_FP64.cpp
polycon/lib/polycon_bindings_03_FP64.cpython-310-darwin.so
polycon/lib/polycon_bindings_04_FP64.cpp
polycon/lib/polycon_bindings_04_FP64.cpython-310-darwin.so
polycon/lib/polycon_bindings_05_FP64.cpp
polycon/lib/polycon_bindings_05_FP64.cpython-310-darwin.so
polycon/lib/polycon_bindings_06_FP64.cpp
polycon/lib/polycon_bindings_06_FP64.cpython-310-darwin.so
polycon/lib/polycon_bindings_07_FP64.cpp
polycon/lib/polycon_bindings_07_FP64.cpython-310-darwin.so
polycon/lib/polycon_bindings_08_FP64.cpp
polycon/lib/polycon_bindings_08_FP64.cpython-310-darwin.so
polycon/lib/polycon_bindings_09_FP64.cpp
polycon/lib/polycon_bindings_09_FP64.cpython-310-darwin.so
polycon/lib/polycon_bindings_10_FP64.cpp
polycon/lib/polycon_bindings_10_FP64.cpython-310-darwin.so
polycon/lib/type_promote.py
polycon-2024.8.30.0.dist-info/METADATA
polycon-2024.8.30.0.dist-info/WHEEL
polycon-2024.8.30.0.dist-info/RECORD
